[
  {
    "_type": "tag",
    "name": "GCFINALIZECOST",
    "path": "C:\\Users\\sunup\\PycharmProjects\\BinCENT\\lua\\src\\lgc.c",
    "pattern": "/^#define GCFINALIZECOST\t/",
    "file": true,
    "language": "C",
    "line": 29,
    "kind": "macro",
    "roles": "def",
    "extras": "fileScope",
    "end": 29
  },
  {
    "_type": "tag",
    "name": "GCSTEPSIZE",
    "path": "C:\\Users\\sunup\\PycharmProjects\\BinCENT\\lua\\src\\lgc.c",
    "pattern": "/^#define GCSTEPSIZE\t/",
    "file": true,
    "language": "C",
    "line": 26,
    "kind": "macro",
    "roles": "def",
    "extras": "fileScope",
    "end": 26
  },
  {
    "_type": "tag",
    "name": "GCSWEEPCOST",
    "path": "C:\\Users\\sunup\\PycharmProjects\\BinCENT\\lua\\src\\lgc.c",
    "pattern": "/^#define GCSWEEPCOST\t/",
    "file": true,
    "language": "C",
    "line": 28,
    "kind": "macro",
    "roles": "def",
    "extras": "fileScope",
    "end": 28
  },
  {
    "_type": "tag",
    "name": "GCSWEEPMAX",
    "path": "C:\\Users\\sunup\\PycharmProjects\\BinCENT\\lua\\src\\lgc.c",
    "pattern": "/^#define GCSWEEPMAX\t/",
    "file": true,
    "language": "C",
    "line": 27,
    "kind": "macro",
    "roles": "def",
    "extras": "fileScope",
    "end": 27
  },
  {
    "_type": "tag",
    "name": "GCTM",
    "path": "C:\\Users\\sunup\\PycharmProjects\\BinCENT\\lua\\src\\lgc.c",
    "pattern": "/^static void GCTM (lua_State *L) {$/",
    "file": true,
    "language": "C",
    "line": 445,
    "typeref": "typename:void",
    "kind": "function",
    "signature": "(lua_State * L)",
    "roles": "def",
    "extras": "fileScope",
    "end": 471
  },
  {
    "_type": "tag",
    "name": "KEYWEAK",
    "path": "C:\\Users\\sunup\\PycharmProjects\\BinCENT\\lua\\src\\lgc.c",
    "pattern": "/^#define KEYWEAK         bitmask(KEYWEAKB/",
    "file": true,
    "language": "C",
    "line": 47,
    "kind": "macro",
    "roles": "def",
    "extras": "fileScope",
    "end": 47
  },
  {
    "_type": "tag",
    "name": "L",
    "path": "C:\\Users\\sunup\\PycharmProjects\\BinCENT\\lua\\src\\lgc.c",
    "pattern": "/^#define sweepwholelist(L,p)\tsweeplist(L,p,MAX_LUMEM)$/",
    "language": "C",
    "line": 404,
    "kind": "macroparam",
    "scope": "sweepwholelist",
    "scopeKind": "macro",
    "roles": "def",
    "nth": 0
  },
  {
    "_type": "tag",
    "name": "L",
    "path": "C:\\Users\\sunup\\PycharmProjects\\BinCENT\\lua\\src\\lgc.c",
    "pattern": "/^size_t luaC_separateudata (lua_State *L, int all) {$/",
    "file": true,
    "language": "C",
    "line": 128,
    "typeref": "typename:lua_State *",
    "kind": "parameter",
    "scope": "luaC_separateudata",
    "scopeKind": "function",
    "roles": "def",
    "extras": "fileScope",
    "nth": 0
  },
  {
    "_type": "tag",
    "name": "L",
    "path": "C:\\Users\\sunup\\PycharmProjects\\BinCENT\\lua\\src\\lgc.c",
    "pattern": "/^static GCObject **sweeplist (lua_State *L, GCObject **p, lu_mem count) {$/",
    "file": true,
    "language": "C",
    "line": 407,
    "typeref": "typename:lua_State *",
    "kind": "parameter",
    "scope": "sweeplist",
    "scopeKind": "function",
    "roles": "def",
    "extras": "fileScope",
    "nth": 0
  },
  {
    "_type": "tag",
    "name": "L",
    "path": "C:\\Users\\sunup\\PycharmProjects\\BinCENT\\lua\\src\\lgc.c",
    "pattern": "/^static l_mem singlestep (lua_State *L) {$/",
    "file": true,
    "language": "C",
    "line": 556,
    "typeref": "typename:lua_State *",
    "kind": "parameter",
    "scope": "singlestep",
    "scopeKind": "function",
    "roles": "def",
    "extras": "fileScope",
    "nth": 0
  },
  {
    "_type": "tag",
    "name": "L",
    "path": "C:\\Users\\sunup\\PycharmProjects\\BinCENT\\lua\\src\\lgc.c",
    "pattern": "/^static void GCTM (lua_State *L) {$/",
    "file": true,
    "language": "C",
    "line": 445,
    "typeref": "typename:lua_State *",
    "kind": "parameter",
    "scope": "GCTM",
    "scopeKind": "function",
    "roles": "def",
    "extras": "fileScope",
    "nth": 0
  },
  {
    "_type": "tag",
    "name": "L",
    "path": "C:\\Users\\sunup\\PycharmProjects\\BinCENT\\lua\\src\\lgc.c",
    "pattern": "/^static void atomic (lua_State *L) {$/",
    "file": true,
    "language": "C",
    "line": 525,
    "typeref": "typename:lua_State *",
    "kind": "parameter",
    "scope": "atomic",
    "scopeKind": "function",
    "roles": "def",
    "extras": "fileScope",
    "nth": 0
  },
  {
    "_type": "tag",
    "name": "L",
    "path": "C:\\Users\\sunup\\PycharmProjects\\BinCENT\\lua\\src\\lgc.c",
    "pattern": "/^static void checkSizes (lua_State *L) {$/",
    "file": true,
    "language": "C",
    "line": 431,
    "typeref": "typename:lua_State *",
    "kind": "parameter",
    "scope": "checkSizes",
    "scopeKind": "function",
    "roles": "def",
    "extras": "fileScope",
    "nth": 0
  },
  {
    "_type": "tag",
    "name": "L",
    "path": "C:\\Users\\sunup\\PycharmProjects\\BinCENT\\lua\\src\\lgc.c",
    "pattern": "/^static void checkstacksizes (lua_State *L, StkId max) {$/",
    "file": true,
    "language": "C",
    "line": 241,
    "typeref": "typename:lua_State *",
    "kind": "parameter",
    "scope": "checkstacksizes",
    "scopeKind": "function",
    "roles": "def",
    "extras": "fileScope",
    "nth": 0
  },
  {
    "_type": "tag",
    "name": "L",
    "path": "C:\\Users\\sunup\\PycharmProjects\\BinCENT\\lua\\src\\lgc.c",
    "pattern": "/^static void freeobj (lua_State *L, GCObject *o) {$/",
    "file": true,
    "language": "C",
    "line": 378,
    "typeref": "typename:lua_State *",
    "kind": "parameter",
    "scope": "freeobj",
    "scopeKind": "function",
    "roles": "def",
    "extras": "fileScope",
    "nth": 0
  },
  {
    "_type": "tag",
    "name": "L",
    "path": "C:\\Users\\sunup\\PycharmProjects\\BinCENT\\lua\\src\\lgc.c",
    "pattern": "/^static void markroot (lua_State *L) {$/",
    "file": true,
    "language": "C",
    "line": 501,
    "typeref": "typename:lua_State *",
    "kind": "parameter",
    "scope": "markroot",
    "scopeKind": "function",
    "roles": "def",
    "extras": "fileScope",
    "nth": 0
  },
  {
    "_type": "tag",
    "name": "L",
    "path": "C:\\Users\\sunup\\PycharmProjects\\BinCENT\\lua\\src\\lgc.c",
    "pattern": "/^void luaC_barrierback (lua_State *L, Table *t) {$/",
    "file": true,
    "language": "C",
    "line": 674,
    "typeref": "typename:lua_State *",
    "kind": "parameter",
    "scope": "luaC_barrierback",
    "scopeKind": "function",
    "roles": "def",
    "extras": "fileScope",
    "nth": 0
  },
  {
    "_type": "tag",
    "name": "L",
    "path": "C:\\Users\\sunup\\PycharmProjects\\BinCENT\\lua\\src\\lgc.c",
    "pattern": "/^void luaC_barrierf (lua_State *L, GCObject *o, GCObject *v) {$/",
    "file": true,
    "language": "C",
    "line": 661,
    "typeref": "typename:lua_State *",
    "kind": "parameter",
    "scope": "luaC_barrierf",
    "scopeKind": "function",
    "roles": "def",
    "extras": "fileScope",
    "nth": 0
  },
  {
    "_type": "tag",
    "name": "L",
    "path": "C:\\Users\\sunup\\PycharmProjects\\BinCENT\\lua\\src\\lgc.c",
    "pattern": "/^void luaC_callGCTM (lua_State *L) {$/",
    "file": true,
    "language": "C",
    "line": 477,
    "typeref": "typename:lua_State *",
    "kind": "parameter",
    "scope": "luaC_callGCTM",
    "scopeKind": "function",
    "roles": "def",
    "extras": "fileScope",
    "nth": 0
  },
  {
    "_type": "tag",
    "name": "L",
    "path": "C:\\Users\\sunup\\PycharmProjects\\BinCENT\\lua\\src\\lgc.c",
    "pattern": "/^void luaC_freeall (lua_State *L) {$/",
    "file": true,
    "language": "C",
    "line": 483,
    "typeref": "typename:lua_State *",
    "kind": "parameter",
    "scope": "luaC_freeall",
    "scopeKind": "function",
    "roles": "def",
    "extras": "fileScope",
    "nth": 0
  },
  {
    "_type": "tag",
    "name": "L",
    "path": "C:\\Users\\sunup\\PycharmProjects\\BinCENT\\lua\\src\\lgc.c",
    "pattern": "/^void luaC_fullgc (lua_State *L) {$/",
    "file": true,
    "language": "C",
    "line": 635,
    "typeref": "typename:lua_State *",
    "kind": "parameter",
    "scope": "luaC_fullgc",
    "scopeKind": "function",
    "roles": "def",
    "extras": "fileScope",
    "nth": 0
  },
  {
    "_type": "tag",
    "name": "L",
    "path": "C:\\Users\\sunup\\PycharmProjects\\BinCENT\\lua\\src\\lgc.c",
    "pattern": "/^void luaC_link (lua_State *L, GCObject *o, lu_byte tt) {$/",
    "file": true,
    "language": "C",
    "line": 685,
    "typeref": "typename:lua_State *",
    "kind": "parameter",
    "scope": "luaC_link",
    "scopeKind": "function",
    "roles": "def",
    "extras": "fileScope",
    "nth": 0
  },
  {
    "_type": "tag",
    "name": "L",
    "path": "C:\\Users\\sunup\\PycharmProjects\\BinCENT\\lua\\src\\lgc.c",
    "pattern": "/^void luaC_linkupval (lua_State *L, UpVal *uv) {$/",
    "file": true,
    "language": "C",
    "line": 694,
    "typeref": "typename:lua_State *",
    "kind": "parameter",
    "scope": "luaC_linkupval",
    "scopeKind": "function",
    "roles": "def",
    "extras": "fileScope",
    "nth": 0
  },
  {
    "_type": "tag",
    "name": "L",
    "path": "C:\\Users\\sunup\\PycharmProjects\\BinCENT\\lua\\src\\lgc.c",
    "pattern": "/^void luaC_step (lua_State *L) {$/",
    "file": true,
    "language": "C",
    "line": 610,
    "typeref": "typename:lua_State *",
    "kind": "parameter",
    "scope": "luaC_step",
    "scopeKind": "function",
    "roles": "def",
    "extras": "fileScope",
    "nth": 0
  },
  {
    "_type": "tag",
    "name": "LUA_CORE",
    "path": "C:\\Users\\sunup\\PycharmProjects\\BinCENT\\lua\\src\\lgc.c",
    "pattern": "/^#define LUA_CORE$/",
    "file": true,
    "language": "C",
    "line": 10,
    "kind": "macro",
    "roles": "def",
    "extras": "fileScope",
    "end": 10
  },
  {
    "_type": "tag",
    "name": "VALUEWEAK",
    "path": "C:\\Users\\sunup\\PycharmProjects\\BinCENT\\lua\\src\\lgc.c",
    "pattern": "/^#define VALUEWEAK       bitmask(VALUEWEAKB/",
    "file": true,
    "language": "C",
    "line": 48,
    "kind": "macro",
    "roles": "def",
    "extras": "fileScope",
    "end": 48
  },
  {
    "_type": "tag",
    "name": "all",
    "path": "C:\\Users\\sunup\\PycharmProjects\\BinCENT\\lua\\src\\lgc.c",
    "pattern": "/^size_t luaC_separateudata (lua_State *L, int all) {$/",
    "file": true,
    "language": "C",
    "line": 128,
    "typeref": "typename:int",
    "kind": "parameter",
    "scope": "luaC_separateudata",
    "scopeKind": "function",
    "roles": "def",
    "extras": "fileScope",
    "nth": 1
  },
  {
    "_type": "tag",
    "name": "atomic",
    "path": "C:\\Users\\sunup\\PycharmProjects\\BinCENT\\lua\\src\\lgc.c",
    "pattern": "/^static void atomic (lua_State *L) {$/",
    "file": true,
    "language": "C",
    "line": 525,
    "typeref": "typename:void",
    "kind": "function",
    "signature": "(lua_State * L)",
    "roles": "def",
    "extras": "fileScope",
    "end": 553
  },
  {
    "_type": "tag",
    "name": "black2gray",
    "path": "C:\\Users\\sunup\\PycharmProjects\\BinCENT\\lua\\src\\lgc.c",
    "pattern": "/^#define black2gray(/",
    "file": true,
    "language": "C",
    "line": 38,
    "kind": "macro",
    "signature": "(x)",
    "roles": "def",
    "extras": "fileScope",
    "end": 38
  },
  {
    "_type": "tag",
    "name": "checkSizes",
    "path": "C:\\Users\\sunup\\PycharmProjects\\BinCENT\\lua\\src\\lgc.c",
    "pattern": "/^static void checkSizes (lua_State *L) {$/",
    "file": true,
    "language": "C",
    "line": 431,
    "typeref": "typename:void",
    "kind": "function",
    "signature": "(lua_State * L)",
    "roles": "def",
    "extras": "fileScope",
    "end": 442
  },
  {
    "_type": "tag",
    "name": "checkstacksizes",
    "path": "C:\\Users\\sunup\\PycharmProjects\\BinCENT\\lua\\src\\lgc.c",
    "pattern": "/^static void checkstacksizes (lua_State *L, StkId max) {$/",
    "file": true,
    "language": "C",
    "line": 241,
    "typeref": "typename:void",
    "kind": "function",
    "signature": "(lua_State * L,StkId max)",
    "roles": "def",
    "extras": "fileScope",
    "end": 253
  },
  {
    "_type": "tag",
    "name": "ci",
    "path": "C:\\Users\\sunup\\PycharmProjects\\BinCENT\\lua\\src\\lgc.c",
    "pattern": "/^  CallInfo *ci;$/",
    "file": true,
    "language": "C",
    "line": 258,
    "typeref": "typename:CallInfo *",
    "kind": "local",
    "scope": "traversestack",
    "scopeKind": "function",
    "roles": "def",
    "extras": "fileScope",
    "end": 258
  },
  {
    "_type": "tag",
    "name": "ci_used",
    "path": "C:\\Users\\sunup\\PycharmProjects\\BinCENT\\lua\\src\\lgc.c",
    "pattern": "/^  int ci_used = cast_int(L->ci - L->base_ci);  \\/* number of `ci' in use *\\/$/",
    "file": true,
    "language": "C",
    "line": 242,
    "typeref": "typename:int",
    "kind": "local",
    "scope": "checkstacksizes",
    "scopeKind": "function",
    "roles": "def",
    "extras": "fileScope",
    "end": 242
  },
  {
    "_type": "tag",
    "name": "cl",
    "path": "C:\\Users\\sunup\\PycharmProjects\\BinCENT\\lua\\src\\lgc.c",
    "pattern": "/^      Closure *cl = gco2cl(o);$/",
    "file": true,
    "language": "C",
    "line": 291,
    "typeref": "typename:Closure *",
    "kind": "local",
    "scope": "propagatemark",
    "scopeKind": "function",
    "roles": "def",
    "extras": "fileScope",
    "end": 291
  },
  {
    "_type": "tag",
    "name": "cl",
    "path": "C:\\Users\\sunup\\PycharmProjects\\BinCENT\\lua\\src\\lgc.c",
    "pattern": "/^static void traverseclosure (global_State *g, Closure *cl) {$/",
    "file": true,
    "language": "C",
    "line": 224,
    "typeref": "typename:Closure *",
    "kind": "parameter",
    "scope": "traverseclosure",
    "scopeKind": "function",
    "roles": "def",
    "extras": "fileScope",
    "nth": 1
  },
  {
    "_type": "tag",
    "name": "cleartable",
    "path": "C:\\Users\\sunup\\PycharmProjects\\BinCENT\\lua\\src\\lgc.c",
    "pattern": "/^static void cleartable (GCObject *l) {$/",
    "file": true,
    "language": "C",
    "line": 351,
    "typeref": "typename:void",
    "kind": "function",
    "signature": "(GCObject * l)",
    "roles": "def",
    "extras": "fileScope",
    "end": 375
  },
  {
    "_type": "tag",
    "name": "count",
    "path": "C:\\Users\\sunup\\PycharmProjects\\BinCENT\\lua\\src\\lgc.c",
    "pattern": "/^static GCObject **sweeplist (lua_State *L, GCObject **p, lu_mem count) {$/",
    "file": true,
    "language": "C",
    "line": 407,
    "typeref": "typename:lu_mem",
    "kind": "parameter",
    "scope": "sweeplist",
    "scopeKind": "function",
    "roles": "def",
    "extras": "fileScope",
    "nth": 2
  },
  {
    "_type": "tag",
    "name": "curr",
    "path": "C:\\Users\\sunup\\PycharmProjects\\BinCENT\\lua\\src\\lgc.c",
    "pattern": "/^  GCObject *curr;$/",
    "file": true,
    "language": "C",
    "line": 132,
    "typeref": "typename:GCObject *",
    "kind": "local",
    "scope": "luaC_separateudata",
    "scopeKind": "function",
    "roles": "def",
    "extras": "fileScope",
    "end": 132
  },
  {
    "_type": "tag",
    "name": "curr",
    "path": "C:\\Users\\sunup\\PycharmProjects\\BinCENT\\lua\\src\\lgc.c",
    "pattern": "/^  GCObject *curr;$/",
    "file": true,
    "language": "C",
    "line": 408,
    "typeref": "typename:GCObject *",
    "kind": "local",
    "scope": "sweeplist",
    "scopeKind": "function",
    "roles": "def",
    "extras": "fileScope",
    "end": 408
  },
  {
    "_type": "tag",
    "name": "deadmask",
    "path": "C:\\Users\\sunup\\PycharmProjects\\BinCENT\\lua\\src\\lgc.c",
    "pattern": "/^  int deadmask = otherwhite(g);$/",
    "file": true,
    "language": "C",
    "line": 410,
    "typeref": "typename:int",
    "kind": "local",
    "scope": "sweeplist",
    "scopeKind": "function",
    "roles": "def",
    "extras": "fileScope",
    "end": 410
  },
  {
    "_type": "tag",
    "name": "deadmem",
    "path": "C:\\Users\\sunup\\PycharmProjects\\BinCENT\\lua\\src\\lgc.c",
    "pattern": "/^  size_t deadmem = 0;$/",
    "file": true,
    "language": "C",
    "line": 130,
    "typeref": "typename:size_t",
    "kind": "local",
    "scope": "luaC_separateudata",
    "scopeKind": "function",
    "roles": "def",
    "extras": "fileScope",
    "end": 130
  },
  {
    "_type": "tag",
    "name": "f",
    "path": "C:\\Users\\sunup\\PycharmProjects\\BinCENT\\lua\\src\\lgc.c",
    "pattern": "/^static void traverseproto (global_State *g, Proto *f) {$/",
    "file": true,
    "language": "C",
    "line": 203,
    "typeref": "typename:Proto *",
    "kind": "parameter",
    "scope": "traverseproto",
    "scopeKind": "function",
    "roles": "def",
    "extras": "fileScope",
    "nth": 1
  },
  {
    "_type": "tag",
    "name": "freeobj",
    "path": "C:\\Users\\sunup\\PycharmProjects\\BinCENT\\lua\\src\\lgc.c",
    "pattern": "/^static void freeobj (lua_State *L, GCObject *o) {$/",
    "file": true,
    "language": "C",
    "line": 378,
    "typeref": "typename:void",
    "kind": "function",
    "signature": "(lua_State * L,GCObject * o)",
    "roles": "def",
    "extras": "fileScope",
    "end": 400
  },
  {
    "_type": "tag",
    "name": "g",
    "path": "C:\\Users\\sunup\\PycharmProjects\\BinCENT\\lua\\src\\lgc.c",
    "pattern": "/^  global_State *g = G(L);$/",
    "file": true,
    "language": "C",
    "line": 129,
    "typeref": "typename:global_State *",
    "kind": "local",
    "scope": "luaC_separateudata",
    "scopeKind": "function",
    "roles": "def",
    "extras": "fileScope",
    "end": 129
  },
  {
    "_type": "tag",
    "name": "g",
    "path": "C:\\Users\\sunup\\PycharmProjects\\BinCENT\\lua\\src\\lgc.c",
    "pattern": "/^  global_State *g = G(L);$/",
    "file": true,
    "language": "C",
    "line": 409,
    "typeref": "typename:global_State *",
    "kind": "local",
    "scope": "sweeplist",
    "scopeKind": "function",
    "roles": "def",
    "extras": "fileScope",
    "end": 409
  },
  {
    "_type": "tag",
    "name": "g",
    "path": "C:\\Users\\sunup\\PycharmProjects\\BinCENT\\lua\\src\\lgc.c",
    "pattern": "/^  global_State *g = G(L);$/",
    "file": true,
    "language": "C",
    "line": 432,
    "typeref": "typename:global_State *",
    "kind": "local",
    "scope": "checkSizes",
    "scopeKind": "function",
    "roles": "def",
    "extras": "fileScope",
    "end": 432
  },
  {
    "_type": "tag",
    "name": "g",
    "path": "C:\\Users\\sunup\\PycharmProjects\\BinCENT\\lua\\src\\lgc.c",
    "pattern": "/^  global_State *g = G(L);$/",
    "file": true,
    "language": "C",
    "line": 446,
    "typeref": "typename:global_State *",
    "kind": "local",
    "scope": "GCTM",
    "scopeKind": "function",
    "roles": "def",
    "extras": "fileScope",
    "end": 446
  },
  {
    "_type": "tag",
    "name": "g",
    "path": "C:\\Users\\sunup\\PycharmProjects\\BinCENT\\lua\\src\\lgc.c",
    "pattern": "/^  global_State *g = G(L);$/",
    "file": true,
    "language": "C",
    "line": 484,
    "typeref": "typename:global_State *",
    "kind": "local",
    "scope": "luaC_freeall",
    "scopeKind": "function",
    "roles": "def",
    "extras": "fileScope",
    "end": 484
  },
  {
    "_type": "tag",
    "name": "g",
    "path": "C:\\Users\\sunup\\PycharmProjects\\BinCENT\\lua\\src\\lgc.c",
    "pattern": "/^  global_State *g = G(L);$/",
    "file": true,
    "language": "C",
    "line": 502,
    "typeref": "typename:global_State *",
    "kind": "local",
    "scope": "markroot",
    "scopeKind": "function",
    "roles": "def",
    "extras": "fileScope",
    "end": 502
  },
  {
    "_type": "tag",
    "name": "g",
    "path": "C:\\Users\\sunup\\PycharmProjects\\BinCENT\\lua\\src\\lgc.c",
    "pattern": "/^  global_State *g = G(L);$/",
    "file": true,
    "language": "C",
    "line": 526,
    "typeref": "typename:global_State *",
    "kind": "local",
    "scope": "atomic",
    "scopeKind": "function",
    "roles": "def",
    "extras": "fileScope",
    "end": 526
  },
  {
    "_type": "tag",
    "name": "g",
    "path": "C:\\Users\\sunup\\PycharmProjects\\BinCENT\\lua\\src\\lgc.c",
    "pattern": "/^  global_State *g = G(L);$/",
    "file": true,
    "language": "C",
    "line": 557,
    "typeref": "typename:global_State *",
    "kind": "local",
    "scope": "singlestep",
    "scopeKind": "function",
    "roles": "def",
    "extras": "fileScope",
    "end": 557
  },
  {
    "_type": "tag",
    "name": "g",
    "path": "C:\\Users\\sunup\\PycharmProjects\\BinCENT\\lua\\src\\lgc.c",
    "pattern": "/^  global_State *g = G(L);$/",
    "file": true,
    "language": "C",
    "line": 611,
    "typeref": "typename:global_State *",
    "kind": "local",
    "scope": "luaC_step",
    "scopeKind": "function",
    "roles": "def",
    "extras": "fileScope",
    "end": 611
  },
  {
    "_type": "tag",
    "name": "g",
    "path": "C:\\Users\\sunup\\PycharmProjects\\BinCENT\\lua\\src\\lgc.c",
    "pattern": "/^  global_State *g = G(L);$/",
    "file": true,
    "language": "C",
    "line": 636,
    "typeref": "typename:global_State *",
    "kind": "local",
    "scope": "luaC_fullgc",
    "scopeKind": "function",
    "roles": "def",
    "extras": "fileScope",
    "end": 636
  },
  {
    "_type": "tag",
    "name": "g",
    "path": "C:\\Users\\sunup\\PycharmProjects\\BinCENT\\lua\\src\\lgc.c",
    "pattern": "/^  global_State *g = G(L);$/",
    "file": true,
    "language": "C",
    "line": 662,
    "typeref": "typename:global_State *",
    "kind": "local",
    "scope": "luaC_barrierf",
    "scopeKind": "function",
    "roles": "def",
    "extras": "fileScope",
    "end": 662
  },
  {
    "_type": "tag",
    "name": "g",
    "path": "C:\\Users\\sunup\\PycharmProjects\\BinCENT\\lua\\src\\lgc.c",
    "pattern": "/^  global_State *g = G(L);$/",
    "file": true,
    "language": "C",
    "line": 675,
    "typeref": "typename:global_State *",
    "kind": "local",
    "scope": "luaC_barrierback",
    "scopeKind": "function",
    "roles": "def",
    "extras": "fileScope",
    "end": 675
  },
  {
    "_type": "tag",
    "name": "g",
    "path": "C:\\Users\\sunup\\PycharmProjects\\BinCENT\\lua\\src\\lgc.c",
    "pattern": "/^  global_State *g = G(L);$/",
    "file": true,
    "language": "C",
    "line": 686,
    "typeref": "typename:global_State *",
    "kind": "local",
    "scope": "luaC_link",
    "scopeKind": "function",
    "roles": "def",
    "extras": "fileScope",
    "end": 686
  },
  {
    "_type": "tag",
    "name": "g",
    "path": "C:\\Users\\sunup\\PycharmProjects\\BinCENT\\lua\\src\\lgc.c",
    "pattern": "/^  global_State *g = G(L);$/",
    "file": true,
    "language": "C",
    "line": 695,
    "typeref": "typename:global_State *",
    "kind": "local",
    "scope": "luaC_linkupval",
    "scopeKind": "function",
    "roles": "def",
    "extras": "fileScope",
    "end": 695
  },
  {
    "_type": "tag",
    "name": "g",
    "path": "C:\\Users\\sunup\\PycharmProjects\\BinCENT\\lua\\src\\lgc.c",
    "pattern": "/^#define makewhite(g,x)\t\\\\$/",
    "language": "C",
    "line": 34,
    "kind": "macroparam",
    "scope": "makewhite",
    "scopeKind": "macro",
    "roles": "def",
    "nth": 0
  },
  {
    "_type": "tag",
    "name": "g",
    "path": "C:\\Users\\sunup\\PycharmProjects\\BinCENT\\lua\\src\\lgc.c",
    "pattern": "/^#define markobject(g,t) { if (iswhite(obj2gco(t))) \\\\$/",
    "language": "C",
    "line": 55,
    "kind": "macroparam",
    "scope": "markobject",
    "scopeKind": "macro",
    "roles": "def",
    "nth": 0
  },
  {
    "_type": "tag",
    "name": "g",
    "path": "C:\\Users\\sunup\\PycharmProjects\\BinCENT\\lua\\src\\lgc.c",
    "pattern": "/^#define markvalue(g,o) { checkconsistency(o); \\\\$/",
    "language": "C",
    "line": 52,
    "kind": "macroparam",
    "scope": "markvalue",
    "scopeKind": "macro",
    "roles": "def",
    "nth": 0
  },
  {
    "_type": "tag",
    "name": "g",
    "path": "C:\\Users\\sunup\\PycharmProjects\\BinCENT\\lua\\src\\lgc.c",
    "pattern": "/^#define setthreshold(g)  (g->GCthreshold = (g->estimate\\/100) * g->gcpause)$/",
    "language": "C",
    "line": 59,
    "kind": "macroparam",
    "scope": "setthreshold",
    "scopeKind": "macro",
    "roles": "def",
    "nth": 0
  },
  {
    "_type": "tag",
    "name": "g",
    "path": "C:\\Users\\sunup\\PycharmProjects\\BinCENT\\lua\\src\\lgc.c",
    "pattern": "/^static int traversetable (global_State *g, Table *h) {$/",
    "file": true,
    "language": "C",
    "line": 158,
    "typeref": "typename:global_State *",
    "kind": "parameter",
    "scope": "traversetable",
    "scopeKind": "function",
    "roles": "def",
    "extras": "fileScope",
    "nth": 0
  },
  {
    "_type": "tag",
    "name": "g",
    "path": "C:\\Users\\sunup\\PycharmProjects\\BinCENT\\lua\\src\\lgc.c",
    "pattern": "/^static l_mem propagatemark (global_State *g) {$/",
    "file": true,
    "language": "C",
    "line": 277,
    "typeref": "typename:global_State *",
    "kind": "parameter",
    "scope": "propagatemark",
    "scopeKind": "function",
    "roles": "def",
    "extras": "fileScope",
    "nth": 0
  },
  {
    "_type": "tag",
    "name": "g",
    "path": "C:\\Users\\sunup\\PycharmProjects\\BinCENT\\lua\\src\\lgc.c",
    "pattern": "/^static size_t propagateall (global_State *g) {$/",
    "file": true,
    "language": "C",
    "line": 323,
    "typeref": "typename:global_State *",
    "kind": "parameter",
    "scope": "propagateall",
    "scopeKind": "function",
    "roles": "def",
    "extras": "fileScope",
    "nth": 0
  },
  {
    "_type": "tag",
    "name": "g",
    "path": "C:\\Users\\sunup\\PycharmProjects\\BinCENT\\lua\\src\\lgc.c",
    "pattern": "/^static void markmt (global_State *g) {$/",
    "file": true,
    "language": "C",
    "line": 493,
    "typeref": "typename:global_State *",
    "kind": "parameter",
    "scope": "markmt",
    "scopeKind": "function",
    "roles": "def",
    "extras": "fileScope",
    "nth": 0
  },
  {
    "_type": "tag",
    "name": "g",
    "path": "C:\\Users\\sunup\\PycharmProjects\\BinCENT\\lua\\src\\lgc.c",
    "pattern": "/^static void marktmu (global_State *g) {$/",
    "file": true,
    "language": "C",
    "line": 115,
    "typeref": "typename:global_State *",
    "kind": "parameter",
    "scope": "marktmu",
    "scopeKind": "function",
    "roles": "def",
    "extras": "fileScope",
    "nth": 0
  },
  {
    "_type": "tag",
    "name": "g",
    "path": "C:\\Users\\sunup\\PycharmProjects\\BinCENT\\lua\\src\\lgc.c",
    "pattern": "/^static void reallymarkobject (global_State *g, GCObject *o) {$/",
    "file": true,
    "language": "C",
    "line": 69,
    "typeref": "typename:global_State *",
    "kind": "parameter",
    "scope": "reallymarkobject",
    "scopeKind": "function",
    "roles": "def",
    "extras": "fileScope",
    "nth": 0
  },
  {
    "_type": "tag",
    "name": "g",
    "path": "C:\\Users\\sunup\\PycharmProjects\\BinCENT\\lua\\src\\lgc.c",
    "pattern": "/^static void remarkupvals (global_State *g) {$/",
    "file": true,
    "language": "C",
    "line": 515,
    "typeref": "typename:global_State *",
    "kind": "parameter",
    "scope": "remarkupvals",
    "scopeKind": "function",
    "roles": "def",
    "extras": "fileScope",
    "nth": 0
  },
  {
    "_type": "tag",
    "name": "g",
    "path": "C:\\Users\\sunup\\PycharmProjects\\BinCENT\\lua\\src\\lgc.c",
    "pattern": "/^static void traverseclosure (global_State *g, Closure *cl) {$/",
    "file": true,
    "language": "C",
    "line": 224,
    "typeref": "typename:global_State *",
    "kind": "parameter",
    "scope": "traverseclosure",
    "scopeKind": "function",
    "roles": "def",
    "extras": "fileScope",
    "nth": 0
  },
  {
    "_type": "tag",
    "name": "g",
    "path": "C:\\Users\\sunup\\PycharmProjects\\BinCENT\\lua\\src\\lgc.c",
    "pattern": "/^static void traverseproto (global_State *g, Proto *f) {$/",
    "file": true,
    "language": "C",
    "line": 203,
    "typeref": "typename:global_State *",
    "kind": "parameter",
    "scope": "traverseproto",
    "scopeKind": "function",
    "roles": "def",
    "extras": "fileScope",
    "nth": 0
  },
  {
    "_type": "tag",
    "name": "g",
    "path": "C:\\Users\\sunup\\PycharmProjects\\BinCENT\\lua\\src\\lgc.c",
    "pattern": "/^static void traversestack (global_State *g, lua_State *l) {$/",
    "file": true,
    "language": "C",
    "line": 256,
    "typeref": "typename:global_State *",
    "kind": "parameter",
    "scope": "traversestack",
    "scopeKind": "function",
    "roles": "def",
    "extras": "fileScope",
    "nth": 0
  },
  {
    "_type": "tag",
    "name": "h",
    "path": "C:\\Users\\sunup\\PycharmProjects\\BinCENT\\lua\\src\\lgc.c",
    "pattern": "/^      Table *h = gco2h(o);$/",
    "file": true,
    "language": "C",
    "line": 283,
    "typeref": "typename:Table *",
    "kind": "local",
    "scope": "propagatemark",
    "scopeKind": "function",
    "roles": "def",
    "extras": "fileScope",
    "end": 283
  },
  {
    "_type": "tag",
    "name": "h",
    "path": "C:\\Users\\sunup\\PycharmProjects\\BinCENT\\lua\\src\\lgc.c",
    "pattern": "/^    Table *h = gco2h(l);$/",
    "file": true,
    "language": "C",
    "line": 353,
    "typeref": "typename:Table *",
    "kind": "local",
    "scope": "cleartable",
    "scopeKind": "function",
    "roles": "def",
    "extras": "fileScope",
    "end": 353
  },
  {
    "_type": "tag",
    "name": "h",
    "path": "C:\\Users\\sunup\\PycharmProjects\\BinCENT\\lua\\src\\lgc.c",
    "pattern": "/^static int traversetable (global_State *g, Table *h) {$/",
    "file": true,
    "language": "C",
    "line": 158,
    "typeref": "typename:Table *",
    "kind": "parameter",
    "scope": "traversetable",
    "scopeKind": "function",
    "roles": "def",
    "extras": "fileScope",
    "nth": 1
  },
  {
    "_type": "tag",
    "name": "i",
    "path": "C:\\Users\\sunup\\PycharmProjects\\BinCENT\\lua\\src\\lgc.c",
    "pattern": "/^    int i = h->sizearray;$/",
    "file": true,
    "language": "C",
    "line": 354,
    "typeref": "typename:int",
    "kind": "local",
    "scope": "cleartable",
    "scopeKind": "function",
    "roles": "def",
    "extras": "fileScope",
    "end": 354
  },
  {
    "_type": "tag",
    "name": "i",
    "path": "C:\\Users\\sunup\\PycharmProjects\\BinCENT\\lua\\src\\lgc.c",
    "pattern": "/^    int i;$/",
    "file": true,
    "language": "C",
    "line": 227,
    "typeref": "typename:int",
    "kind": "local",
    "scope": "traverseclosure",
    "scopeKind": "function",
    "roles": "def",
    "extras": "fileScope",
    "end": 227
  },
  {
    "_type": "tag",
    "name": "i",
    "path": "C:\\Users\\sunup\\PycharmProjects\\BinCENT\\lua\\src\\lgc.c",
    "pattern": "/^    int i;$/",
    "file": true,
    "language": "C",
    "line": 232,
    "typeref": "typename:int",
    "kind": "local",
    "scope": "traverseclosure",
    "scopeKind": "function",
    "roles": "def",
    "extras": "fileScope",
    "end": 232
  },
  {
    "_type": "tag",
    "name": "i",
    "path": "C:\\Users\\sunup\\PycharmProjects\\BinCENT\\lua\\src\\lgc.c",
    "pattern": "/^  int i;$/",
    "file": true,
    "language": "C",
    "line": 159,
    "typeref": "typename:int",
    "kind": "local",
    "scope": "traversetable",
    "scopeKind": "function",
    "roles": "def",
    "extras": "fileScope",
    "end": 159
  },
  {
    "_type": "tag",
    "name": "i",
    "path": "C:\\Users\\sunup\\PycharmProjects\\BinCENT\\lua\\src\\lgc.c",
    "pattern": "/^  int i;$/",
    "file": true,
    "language": "C",
    "line": 204,
    "typeref": "typename:int",
    "kind": "local",
    "scope": "traverseproto",
    "scopeKind": "function",
    "roles": "def",
    "extras": "fileScope",
    "end": 204
  },
  {
    "_type": "tag",
    "name": "i",
    "path": "C:\\Users\\sunup\\PycharmProjects\\BinCENT\\lua\\src\\lgc.c",
    "pattern": "/^  int i;$/",
    "file": true,
    "language": "C",
    "line": 485,
    "typeref": "typename:int",
    "kind": "local",
    "scope": "luaC_freeall",
    "scopeKind": "function",
    "roles": "def",
    "extras": "fileScope",
    "end": 485
  },
  {
    "_type": "tag",
    "name": "i",
    "path": "C:\\Users\\sunup\\PycharmProjects\\BinCENT\\lua\\src\\lgc.c",
    "pattern": "/^  int i;$/",
    "file": true,
    "language": "C",
    "line": 494,
    "typeref": "typename:int",
    "kind": "local",
    "scope": "markmt",
    "scopeKind": "function",
    "roles": "def",
    "extras": "fileScope",
    "end": 494
  },
  {
    "_type": "tag",
    "name": "iscleared",
    "path": "C:\\Users\\sunup\\PycharmProjects\\BinCENT\\lua\\src\\lgc.c",
    "pattern": "/^static int iscleared (const TValue *o, int iskey) {$/",
    "file": true,
    "language": "C",
    "line": 337,
    "typeref": "typename:int",
    "kind": "function",
    "signature": "(const TValue * o,int iskey)",
    "roles": "def",
    "extras": "fileScope",
    "end": 345
  },
  {
    "_type": "tag",
    "name": "isfinalized",
    "path": "C:\\Users\\sunup\\PycharmProjects\\BinCENT\\lua\\src\\lgc.c",
    "pattern": "/^#define isfinalized(/",
    "file": true,
    "language": "C",
    "line": 43,
    "kind": "macro",
    "signature": "(u)",
    "roles": "def",
    "extras": "fileScope",
    "end": 43
  },
  {
    "_type": "tag",
    "name": "iskey",
    "path": "C:\\Users\\sunup\\PycharmProjects\\BinCENT\\lua\\src\\lgc.c",
    "pattern": "/^static int iscleared (const TValue *o, int iskey) {$/",
    "file": true,
    "language": "C",
    "line": 337,
    "typeref": "typename:int",
    "kind": "parameter",
    "scope": "iscleared",
    "scopeKind": "function",
    "roles": "def",
    "extras": "fileScope",
    "nth": 1
  },
  {
    "_type": "tag",
    "name": "l",
    "path": "C:\\Users\\sunup\\PycharmProjects\\BinCENT\\lua\\src\\lgc.c",
    "pattern": "/^static void cleartable (GCObject *l) {$/",
    "file": true,
    "language": "C",
    "line": 351,
    "typeref": "typename:GCObject *",
    "kind": "parameter",
    "scope": "cleartable",
    "scopeKind": "function",
    "roles": "def",
    "extras": "fileScope",
    "nth": 0
  },
  {
    "_type": "tag",
    "name": "l",
    "path": "C:\\Users\\sunup\\PycharmProjects\\BinCENT\\lua\\src\\lgc.c",
    "pattern": "/^static void traversestack (global_State *g, lua_State *l) {$/",
    "file": true,
    "language": "C",
    "line": 256,
    "typeref": "typename:lua_State *",
    "kind": "parameter",
    "scope": "traversestack",
    "scopeKind": "function",
    "roles": "def",
    "extras": "fileScope",
    "nth": 1
  },
  {
    "_type": "tag",
    "name": "lgc_c",
    "path": "C:\\Users\\sunup\\PycharmProjects\\BinCENT\\lua\\src\\lgc.c",
    "pattern": "/^#define lgc_c$/",
    "file": true,
    "language": "C",
    "line": 9,
    "kind": "macro",
    "roles": "def",
    "extras": "fileScope",
    "end": 9
  },
  {
    "_type": "tag",
    "name": "lim",
    "path": "C:\\Users\\sunup\\PycharmProjects\\BinCENT\\lua\\src\\lgc.c",
    "pattern": "/^  StkId o, lim;$/",
    "file": true,
    "language": "C",
    "line": 257,
    "typeref": "typename:StkId",
    "kind": "local",
    "scope": "traversestack",
    "scopeKind": "function",
    "roles": "def",
    "extras": "fileScope",
    "end": 257
  },
  {
    "_type": "tag",
    "name": "lim",
    "path": "C:\\Users\\sunup\\PycharmProjects\\BinCENT\\lua\\src\\lgc.c",
    "pattern": "/^  l_mem lim = (GCSTEPSIZE\\/100) * g->gcstepmul;$/",
    "file": true,
    "language": "C",
    "line": 612,
    "typeref": "typename:l_mem",
    "kind": "local",
    "scope": "luaC_step",
    "scopeKind": "function",
    "roles": "def",
    "extras": "fileScope",
    "end": 612
  },
  {
    "_type": "tag",
    "name": "luaC_barrierback",
    "path": "C:\\Users\\sunup\\PycharmProjects\\BinCENT\\lua\\src\\lgc.c",
    "pattern": "/^void luaC_barrierback (lua_State *L, Table *t) {$/",
    "language": "C",
    "line": 674,
    "typeref": "typename:void",
    "kind": "function",
    "signature": "(lua_State * L,Table * t)",
    "roles": "def",
    "end": 682
  },
  {
    "_type": "tag",
    "name": "luaC_barrierf",
    "path": "C:\\Users\\sunup\\PycharmProjects\\BinCENT\\lua\\src\\lgc.c",
    "pattern": "/^void luaC_barrierf (lua_State *L, GCObject *o, GCObject *v) {$/",
    "language": "C",
    "line": 661,
    "typeref": "typename:void",
    "kind": "function",
    "signature": "(lua_State * L,GCObject * o,GCObject * v)",
    "roles": "def",
    "end": 671
  },
  {
    "_type": "tag",
    "name": "luaC_callGCTM",
    "path": "C:\\Users\\sunup\\PycharmProjects\\BinCENT\\lua\\src\\lgc.c",
    "pattern": "/^void luaC_callGCTM (lua_State *L) {$/",
    "language": "C",
    "line": 477,
    "typeref": "typename:void",
    "kind": "function",
    "signature": "(lua_State * L)",
    "roles": "def",
    "end": 480
  },
  {
    "_type": "tag",
    "name": "luaC_freeall",
    "path": "C:\\Users\\sunup\\PycharmProjects\\BinCENT\\lua\\src\\lgc.c",
    "pattern": "/^void luaC_freeall (lua_State *L) {$/",
    "language": "C",
    "line": 483,
    "typeref": "typename:void",
    "kind": "function",
    "signature": "(lua_State * L)",
    "roles": "def",
    "end": 490
  },
  {
    "_type": "tag",
    "name": "luaC_fullgc",
    "path": "C:\\Users\\sunup\\PycharmProjects\\BinCENT\\lua\\src\\lgc.c",
    "pattern": "/^void luaC_fullgc (lua_State *L) {$/",
    "language": "C",
    "line": 635,
    "typeref": "typename:void",
    "kind": "function",
    "signature": "(lua_State * L)",
    "roles": "def",
    "end": 658
  },
  {
    "_type": "tag",
    "name": "luaC_link",
    "path": "C:\\Users\\sunup\\PycharmProjects\\BinCENT\\lua\\src\\lgc.c",
    "pattern": "/^void luaC_link (lua_State *L, GCObject *o, lu_byte tt) {$/",
    "language": "C",
    "line": 685,
    "typeref": "typename:void",
    "kind": "function",
    "signature": "(lua_State * L,GCObject * o,lu_byte tt)",
    "roles": "def",
    "end": 691
  },
  {
    "_type": "tag",
    "name": "luaC_linkupval",
    "path": "C:\\Users\\sunup\\PycharmProjects\\BinCENT\\lua\\src\\lgc.c",
    "pattern": "/^void luaC_linkupval (lua_State *L, UpVal *uv) {$/",
    "language": "C",
    "line": 694,
    "typeref": "typename:void",
    "kind": "function",
    "signature": "(lua_State * L,UpVal * uv)",
    "roles": "def",
    "end": 709
  },
  {
    "_type": "tag",
    "name": "luaC_separateudata",
    "path": "C:\\Users\\sunup\\PycharmProjects\\BinCENT\\lua\\src\\lgc.c",
    "pattern": "/^size_t luaC_separateudata (lua_State *L, int all) {$/",
    "language": "C",
    "line": 128,
    "typeref": "typename:size_t",
    "kind": "function",
    "signature": "(lua_State * L,int all)",
    "roles": "def",
    "end": 155
  },
  {
    "_type": "tag",
    "name": "luaC_step",
    "path": "C:\\Users\\sunup\\PycharmProjects\\BinCENT\\lua\\src\\lgc.c",
    "pattern": "/^void luaC_step (lua_State *L) {$/",
    "language": "C",
    "line": 610,
    "typeref": "typename:void",
    "kind": "function",
    "signature": "(lua_State * L)",
    "roles": "def",
    "end": 632
  },
  {
    "_type": "tag",
    "name": "m",
    "path": "C:\\Users\\sunup\\PycharmProjects\\BinCENT\\lua\\src\\lgc.c",
    "pattern": "/^  size_t m = 0;$/",
    "file": true,
    "language": "C",
    "line": 324,
    "typeref": "typename:size_t",
    "kind": "local",
    "scope": "propagateall",
    "scopeKind": "function",
    "roles": "def",
    "extras": "fileScope",
    "end": 324
  },
  {
    "_type": "tag",
    "name": "makewhite",
    "path": "C:\\Users\\sunup\\PycharmProjects\\BinCENT\\lua\\src\\lgc.c",
    "pattern": "/^#define makewhite(/",
    "file": true,
    "language": "C",
    "line": 34,
    "kind": "macro",
    "signature": "(g,x)",
    "roles": "def",
    "extras": "fileScope",
    "end": 35
  },
  {
    "_type": "tag",
    "name": "markfinalized",
    "path": "C:\\Users\\sunup\\PycharmProjects\\BinCENT\\lua\\src\\lgc.c",
    "pattern": "/^#define markfinalized(/",
    "file": true,
    "language": "C",
    "line": 44,
    "kind": "macro",
    "signature": "(u)",
    "roles": "def",
    "extras": "fileScope",
    "end": 44
  },
  {
    "_type": "tag",
    "name": "markmt",
    "path": "C:\\Users\\sunup\\PycharmProjects\\BinCENT\\lua\\src\\lgc.c",
    "pattern": "/^static void markmt (global_State *g) {$/",
    "file": true,
    "language": "C",
    "line": 493,
    "typeref": "typename:void",
    "kind": "function",
    "signature": "(global_State * g)",
    "roles": "def",
    "extras": "fileScope",
    "end": 497
  },
  {
    "_type": "tag",
    "name": "markobject",
    "path": "C:\\Users\\sunup\\PycharmProjects\\BinCENT\\lua\\src\\lgc.c",
    "pattern": "/^#define markobject(/",
    "file": true,
    "language": "C",
    "line": 55,
    "kind": "macro",
    "signature": "(g,t)",
    "roles": "def",
    "extras": "fileScope",
    "end": 56
  },
  {
    "_type": "tag",
    "name": "markroot",
    "path": "C:\\Users\\sunup\\PycharmProjects\\BinCENT\\lua\\src\\lgc.c",
    "pattern": "/^static void markroot (lua_State *L) {$/",
    "file": true,
    "language": "C",
    "line": 501,
    "typeref": "typename:void",
    "kind": "function",
    "signature": "(lua_State * L)",
    "roles": "def",
    "extras": "fileScope",
    "end": 512
  },
  {
    "_type": "tag",
    "name": "marktmu",
    "path": "C:\\Users\\sunup\\PycharmProjects\\BinCENT\\lua\\src\\lgc.c",
    "pattern": "/^static void marktmu (global_State *g) {$/",
    "file": true,
    "language": "C",
    "line": 115,
    "typeref": "typename:void",
    "kind": "function",
    "signature": "(global_State * g)",
    "roles": "def",
    "extras": "fileScope",
    "end": 124
  },
  {
    "_type": "tag",
    "name": "markvalue",
    "path": "C:\\Users\\sunup\\PycharmProjects\\BinCENT\\lua\\src\\lgc.c",
    "pattern": "/^#define markvalue(/",
    "file": true,
    "language": "C",
    "line": 52,
    "kind": "macro",
    "signature": "(g,o)",
    "roles": "def",
    "extras": "fileScope",
    "end": 53
  },
  {
    "_type": "tag",
    "name": "maskmarks",
    "path": "C:\\Users\\sunup\\PycharmProjects\\BinCENT\\lua\\src\\lgc.c",
    "pattern": "/^#define maskmarks\t/",
    "file": true,
    "language": "C",
    "line": 32,
    "kind": "macro",
    "roles": "def",
    "extras": "fileScope",
    "end": 32
  },
  {
    "_type": "tag",
    "name": "max",
    "path": "C:\\Users\\sunup\\PycharmProjects\\BinCENT\\lua\\src\\lgc.c",
    "pattern": "/^static void checkstacksizes (lua_State *L, StkId max) {$/",
    "file": true,
    "language": "C",
    "line": 241,
    "typeref": "typename:StkId",
    "kind": "parameter",
    "scope": "checkstacksizes",
    "scopeKind": "function",
    "roles": "def",
    "extras": "fileScope",
    "nth": 1
  },
  {
    "_type": "tag",
    "name": "mode",
    "path": "C:\\Users\\sunup\\PycharmProjects\\BinCENT\\lua\\src\\lgc.c",
    "pattern": "/^  const TValue *mode;$/",
    "file": true,
    "language": "C",
    "line": 162,
    "typeref": "typename:const TValue *",
    "kind": "local",
    "scope": "traversetable",
    "scopeKind": "function",
    "roles": "def",
    "extras": "fileScope",
    "end": 162
  },
  {
    "_type": "tag",
    "name": "mt",
    "path": "C:\\Users\\sunup\\PycharmProjects\\BinCENT\\lua\\src\\lgc.c",
    "pattern": "/^      Table *mt = gco2u(o)->metatable;$/",
    "file": true,
    "language": "C",
    "line": 77,
    "typeref": "typename:Table *",
    "kind": "local",
    "scope": "reallymarkobject",
    "scopeKind": "function",
    "roles": "def",
    "extras": "fileScope",
    "end": 77
  },
  {
    "_type": "tag",
    "name": "n",
    "path": "C:\\Users\\sunup\\PycharmProjects\\BinCENT\\lua\\src\\lgc.c",
    "pattern": "/^      Node *n = gnode(h, i);$/",
    "file": true,
    "language": "C",
    "line": 366,
    "typeref": "typename:Node *",
    "kind": "local",
    "scope": "cleartable",
    "scopeKind": "function",
    "roles": "def",
    "extras": "fileScope",
    "end": 366
  },
  {
    "_type": "tag",
    "name": "n",
    "path": "C:\\Users\\sunup\\PycharmProjects\\BinCENT\\lua\\src\\lgc.c",
    "pattern": "/^    Node *n = gnode(h, i);$/",
    "file": true,
    "language": "C",
    "line": 185,
    "typeref": "typename:Node *",
    "kind": "local",
    "scope": "traversetable",
    "scopeKind": "function",
    "roles": "def",
    "extras": "fileScope",
    "end": 185
  },
  {
    "_type": "tag",
    "name": "n",
    "path": "C:\\Users\\sunup\\PycharmProjects\\BinCENT\\lua\\src\\lgc.c",
    "pattern": "/^static void removeentry (Node *n) {$/",
    "file": true,
    "language": "C",
    "line": 62,
    "typeref": "typename:Node *",
    "kind": "parameter",
    "scope": "removeentry",
    "scopeKind": "function",
    "roles": "def",
    "extras": "fileScope",
    "nth": 0
  },
  {
    "_type": "tag",
    "name": "newsize",
    "path": "C:\\Users\\sunup\\PycharmProjects\\BinCENT\\lua\\src\\lgc.c",
    "pattern": "/^    size_t newsize = luaZ_sizebuffer(&g->buff) \\/ 2;$/",
    "file": true,
    "language": "C",
    "line": 439,
    "typeref": "typename:size_t",
    "kind": "local",
    "scope": "checkSizes",
    "scopeKind": "function",
    "roles": "def",
    "extras": "fileScope",
    "end": 439
  },
  {
    "_type": "tag",
    "name": "o",
    "path": "C:\\Users\\sunup\\PycharmProjects\\BinCENT\\lua\\src\\lgc.c",
    "pattern": "/^        TValue *o = &h->array[i];$/",
    "file": true,
    "language": "C",
    "line": 359,
    "typeref": "typename:TValue *",
    "kind": "local",
    "scope": "cleartable",
    "scopeKind": "function",
    "roles": "def",
    "extras": "fileScope",
    "end": 359
  },
  {
    "_type": "tag",
    "name": "o",
    "path": "C:\\Users\\sunup\\PycharmProjects\\BinCENT\\lua\\src\\lgc.c",
    "pattern": "/^  GCObject *o = g->gray;$/",
    "file": true,
    "language": "C",
    "line": 278,
    "typeref": "typename:GCObject *",
    "kind": "local",
    "scope": "propagatemark",
    "scopeKind": "function",
    "roles": "def",
    "extras": "fileScope",
    "end": 278
  },
  {
    "_type": "tag",
    "name": "o",
    "path": "C:\\Users\\sunup\\PycharmProjects\\BinCENT\\lua\\src\\lgc.c",
    "pattern": "/^  GCObject *o = g->tmudata->gch.next;  \\/* get first element *\\/$/",
    "file": true,
    "language": "C",
    "line": 447,
    "typeref": "typename:GCObject *",
    "kind": "local",
    "scope": "GCTM",
    "scopeKind": "function",
    "roles": "def",
    "extras": "fileScope",
    "end": 447
  },
  {
    "_type": "tag",
    "name": "o",
    "path": "C:\\Users\\sunup\\PycharmProjects\\BinCENT\\lua\\src\\lgc.c",
    "pattern": "/^  GCObject *o = obj2gco(t);$/",
    "file": true,
    "language": "C",
    "line": 676,
    "typeref": "typename:GCObject *",
    "kind": "local",
    "scope": "luaC_barrierback",
    "scopeKind": "function",
    "roles": "def",
    "extras": "fileScope",
    "end": 676
  },
  {
    "_type": "tag",
    "name": "o",
    "path": "C:\\Users\\sunup\\PycharmProjects\\BinCENT\\lua\\src\\lgc.c",
    "pattern": "/^  GCObject *o = obj2gco(uv);$/",
    "file": true,
    "language": "C",
    "line": 696,
    "typeref": "typename:GCObject *",
    "kind": "local",
    "scope": "luaC_linkupval",
    "scopeKind": "function",
    "roles": "def",
    "extras": "fileScope",
    "end": 696
  },
  {
    "_type": "tag",
    "name": "o",
    "path": "C:\\Users\\sunup\\PycharmProjects\\BinCENT\\lua\\src\\lgc.c",
    "pattern": "/^  StkId o, lim;$/",
    "file": true,
    "language": "C",
    "line": 257,
    "typeref": "typename:StkId",
    "kind": "local",
    "scope": "traversestack",
    "scopeKind": "function",
    "roles": "def",
    "extras": "fileScope",
    "end": 257
  },
  {
    "_type": "tag",
    "name": "o",
    "path": "C:\\Users\\sunup\\PycharmProjects\\BinCENT\\lua\\src\\lgc.c",
    "pattern": "/^#define markvalue(g,o) { checkconsistency(o); \\\\$/",
    "language": "C",
    "line": 52,
    "kind": "macroparam",
    "scope": "markvalue",
    "scopeKind": "macro",
    "roles": "def",
    "nth": 1
  },
  {
    "_type": "tag",
    "name": "o",
    "path": "C:\\Users\\sunup\\PycharmProjects\\BinCENT\\lua\\src\\lgc.c",
    "pattern": "/^static int iscleared (const TValue *o, int iskey) {$/",
    "file": true,
    "language": "C",
    "line": 337,
    "typeref": "typename:const TValue *",
    "kind": "parameter",
    "scope": "iscleared",
    "scopeKind": "function",
    "roles": "def",
    "extras": "fileScope",
    "nth": 0
  },
  {
    "_type": "tag",
    "name": "o",
    "path": "C:\\Users\\sunup\\PycharmProjects\\BinCENT\\lua\\src\\lgc.c",
    "pattern": "/^static void freeobj (lua_State *L, GCObject *o) {$/",
    "file": true,
    "language": "C",
    "line": 378,
    "typeref": "typename:GCObject *",
    "kind": "parameter",
    "scope": "freeobj",
    "scopeKind": "function",
    "roles": "def",
    "extras": "fileScope",
    "nth": 1
  },
  {
    "_type": "tag",
    "name": "o",
    "path": "C:\\Users\\sunup\\PycharmProjects\\BinCENT\\lua\\src\\lgc.c",
    "pattern": "/^static void reallymarkobject (global_State *g, GCObject *o) {$/",
    "file": true,
    "language": "C",
    "line": 69,
    "typeref": "typename:GCObject *",
    "kind": "parameter",
    "scope": "reallymarkobject",
    "scopeKind": "function",
    "roles": "def",
    "extras": "fileScope",
    "nth": 1
  },
  {
    "_type": "tag",
    "name": "o",
    "path": "C:\\Users\\sunup\\PycharmProjects\\BinCENT\\lua\\src\\lgc.c",
    "pattern": "/^void luaC_barrierf (lua_State *L, GCObject *o, GCObject *v) {$/",
    "file": true,
    "language": "C",
    "line": 661,
    "typeref": "typename:GCObject *",
    "kind": "parameter",
    "scope": "luaC_barrierf",
    "scopeKind": "function",
    "roles": "def",
    "extras": "fileScope",
    "nth": 1
  },
  {
    "_type": "tag",
    "name": "o",
    "path": "C:\\Users\\sunup\\PycharmProjects\\BinCENT\\lua\\src\\lgc.c",
    "pattern": "/^void luaC_link (lua_State *L, GCObject *o, lu_byte tt) {$/",
    "file": true,
    "language": "C",
    "line": 685,
    "typeref": "typename:GCObject *",
    "kind": "parameter",
    "scope": "luaC_link",
    "scopeKind": "function",
    "roles": "def",
    "extras": "fileScope",
    "nth": 1
  },
  {
    "_type": "tag",
    "name": "old",
    "path": "C:\\Users\\sunup\\PycharmProjects\\BinCENT\\lua\\src\\lgc.c",
    "pattern": "/^      lu_mem old = g->totalbytes;$/",
    "file": true,
    "language": "C",
    "line": 573,
    "typeref": "typename:lu_mem",
    "kind": "local",
    "scope": "singlestep",
    "scopeKind": "function",
    "roles": "def",
    "extras": "fileScope",
    "end": 573
  },
  {
    "_type": "tag",
    "name": "old",
    "path": "C:\\Users\\sunup\\PycharmProjects\\BinCENT\\lua\\src\\lgc.c",
    "pattern": "/^      lu_mem old = g->totalbytes;$/",
    "file": true,
    "language": "C",
    "line": 582,
    "typeref": "typename:lu_mem",
    "kind": "local",
    "scope": "singlestep",
    "scopeKind": "function",
    "roles": "def",
    "extras": "fileScope",
    "end": 582
  },
  {
    "_type": "tag",
    "name": "oldah",
    "path": "C:\\Users\\sunup\\PycharmProjects\\BinCENT\\lua\\src\\lgc.c",
    "pattern": "/^    lu_byte oldah = L->allowhook;$/",
    "file": true,
    "language": "C",
    "line": 460,
    "typeref": "typename:lu_byte",
    "kind": "local",
    "scope": "GCTM",
    "scopeKind": "function",
    "roles": "def",
    "extras": "fileScope",
    "end": 460
  },
  {
    "_type": "tag",
    "name": "oldt",
    "path": "C:\\Users\\sunup\\PycharmProjects\\BinCENT\\lua\\src\\lgc.c",
    "pattern": "/^    lu_mem oldt = g->GCthreshold;$/",
    "file": true,
    "language": "C",
    "line": 461,
    "typeref": "typename:lu_mem",
    "kind": "local",
    "scope": "GCTM",
    "scopeKind": "function",
    "roles": "def",
    "extras": "fileScope",
    "end": 461
  },
  {
    "_type": "tag",
    "name": "p",
    "path": "C:\\Users\\sunup\\PycharmProjects\\BinCENT\\lua\\src\\lgc.c",
    "pattern": "/^      Proto *p = gco2p(o);$/",
    "file": true,
    "language": "C",
    "line": 308,
    "typeref": "typename:Proto *",
    "kind": "local",
    "scope": "propagatemark",
    "scopeKind": "function",
    "roles": "def",
    "extras": "fileScope",
    "end": 308
  },
  {
    "_type": "tag",
    "name": "p",
    "path": "C:\\Users\\sunup\\PycharmProjects\\BinCENT\\lua\\src\\lgc.c",
    "pattern": "/^  GCObject **p = &g->mainthread->next;$/",
    "file": true,
    "language": "C",
    "line": 131,
    "typeref": "typename:GCObject **",
    "kind": "local",
    "scope": "luaC_separateudata",
    "scopeKind": "function",
    "roles": "def",
    "extras": "fileScope",
    "end": 131
  },
  {
    "_type": "tag",
    "name": "p",
    "path": "C:\\Users\\sunup\\PycharmProjects\\BinCENT\\lua\\src\\lgc.c",
    "pattern": "/^#define sweepwholelist(L,p)\tsweeplist(L,p,MAX_LUMEM)$/",
    "language": "C",
    "line": 404,
    "kind": "macroparam",
    "scope": "sweepwholelist",
    "scopeKind": "macro",
    "roles": "def",
    "nth": 1
  },
  {
    "_type": "tag",
    "name": "p",
    "path": "C:\\Users\\sunup\\PycharmProjects\\BinCENT\\lua\\src\\lgc.c",
    "pattern": "/^static GCObject **sweeplist (lua_State *L, GCObject **p, lu_mem count) {$/",
    "file": true,
    "language": "C",
    "line": 407,
    "typeref": "typename:GCObject **",
    "kind": "parameter",
    "scope": "sweeplist",
    "scopeKind": "function",
    "roles": "def",
    "extras": "fileScope",
    "nth": 1
  },
  {
    "_type": "tag",
    "name": "propagateall",
    "path": "C:\\Users\\sunup\\PycharmProjects\\BinCENT\\lua\\src\\lgc.c",
    "pattern": "/^static size_t propagateall (global_State *g) {$/",
    "file": true,
    "language": "C",
    "line": 323,
    "typeref": "typename:size_t",
    "kind": "function",
    "signature": "(global_State * g)",
    "roles": "def",
    "extras": "fileScope",
    "end": 327
  },
  {
    "_type": "tag",
    "name": "propagatemark",
    "path": "C:\\Users\\sunup\\PycharmProjects\\BinCENT\\lua\\src\\lgc.c",
    "pattern": "/^static l_mem propagatemark (global_State *g) {$/",
    "file": true,
    "language": "C",
    "line": 277,
    "typeref": "typename:l_mem",
    "kind": "function",
    "signature": "(global_State * g)",
    "roles": "def",
    "extras": "fileScope",
    "end": 320
  },
  {
    "_type": "tag",
    "name": "reallymarkobject",
    "path": "C:\\Users\\sunup\\PycharmProjects\\BinCENT\\lua\\src\\lgc.c",
    "pattern": "/^static void reallymarkobject (global_State *g, GCObject *o) {$/",
    "file": true,
    "language": "C",
    "line": 69,
    "typeref": "typename:void",
    "kind": "function",
    "signature": "(global_State * g,GCObject * o)",
    "roles": "def",
    "extras": "fileScope",
    "end": 112
  },
  {
    "_type": "tag",
    "name": "remarkupvals",
    "path": "C:\\Users\\sunup\\PycharmProjects\\BinCENT\\lua\\src\\lgc.c",
    "pattern": "/^static void remarkupvals (global_State *g) {$/",
    "file": true,
    "language": "C",
    "line": 515,
    "typeref": "typename:void",
    "kind": "function",
    "signature": "(global_State * g)",
    "roles": "def",
    "extras": "fileScope",
    "end": 522
  },
  {
    "_type": "tag",
    "name": "removeentry",
    "path": "C:\\Users\\sunup\\PycharmProjects\\BinCENT\\lua\\src\\lgc.c",
    "pattern": "/^static void removeentry (Node *n) {$/",
    "file": true,
    "language": "C",
    "line": 62,
    "typeref": "typename:void",
    "kind": "function",
    "signature": "(Node * n)",
    "roles": "def",
    "extras": "fileScope",
    "end": 66
  },
  {
    "_type": "tag",
    "name": "s",
    "path": "C:\\Users\\sunup\\PycharmProjects\\BinCENT\\lua\\src\\lgc.c",
    "pattern": "/^#define stringmark(s)\treset2bits((s)->tsv.marked, WHITE0BIT, WHITE1BIT)$/",
    "language": "C",
    "line": 40,
    "kind": "macroparam",
    "scope": "stringmark",
    "scopeKind": "macro",
    "roles": "def",
    "nth": 0
  },
  {
    "_type": "tag",
    "name": "s_used",
    "path": "C:\\Users\\sunup\\PycharmProjects\\BinCENT\\lua\\src\\lgc.c",
    "pattern": "/^  int s_used = cast_int(max - L->stack);  \\/* part of stack in use *\\/$/",
    "file": true,
    "language": "C",
    "line": 243,
    "typeref": "typename:int",
    "kind": "local",
    "scope": "checkstacksizes",
    "scopeKind": "function",
    "roles": "def",
    "extras": "fileScope",
    "end": 243
  },
  {
    "_type": "tag",
    "name": "setthreshold",
    "path": "C:\\Users\\sunup\\PycharmProjects\\BinCENT\\lua\\src\\lgc.c",
    "pattern": "/^#define setthreshold(/",
    "file": true,
    "language": "C",
    "line": 59,
    "kind": "macro",
    "signature": "(g)",
    "roles": "def",
    "extras": "fileScope",
    "end": 59
  },
  {
    "_type": "tag",
    "name": "singlestep",
    "path": "C:\\Users\\sunup\\PycharmProjects\\BinCENT\\lua\\src\\lgc.c",
    "pattern": "/^static l_mem singlestep (lua_State *L) {$/",
    "file": true,
    "language": "C",
    "line": 556,
    "typeref": "typename:l_mem",
    "kind": "function",
    "signature": "(lua_State * L)",
    "roles": "def",
    "extras": "fileScope",
    "end": 607
  },
  {
    "_type": "tag",
    "name": "stringmark",
    "path": "C:\\Users\\sunup\\PycharmProjects\\BinCENT\\lua\\src\\lgc.c",
    "pattern": "/^#define stringmark(/",
    "file": true,
    "language": "C",
    "line": 40,
    "kind": "macro",
    "signature": "(s)",
    "roles": "def",
    "extras": "fileScope",
    "end": 40
  },
  {
    "_type": "tag",
    "name": "sweeplist",
    "path": "C:\\Users\\sunup\\PycharmProjects\\BinCENT\\lua\\src\\lgc.c",
    "pattern": "/^static GCObject **sweeplist (lua_State *L, GCObject **p, lu_mem count) {$/",
    "file": true,
    "language": "C",
    "line": 407,
    "typeref": "typename:GCObject **",
    "kind": "function",
    "signature": "(lua_State * L,GCObject ** p,lu_mem count)",
    "roles": "def",
    "extras": "fileScope",
    "end": 428
  },
  {
    "_type": "tag",
    "name": "sweepwholelist",
    "path": "C:\\Users\\sunup\\PycharmProjects\\BinCENT\\lua\\src\\lgc.c",
    "pattern": "/^#define sweepwholelist(/",
    "file": true,
    "language": "C",
    "line": 404,
    "kind": "macro",
    "signature": "(L,p)",
    "roles": "def",
    "extras": "fileScope",
    "end": 404
  },
  {
    "_type": "tag",
    "name": "t",
    "path": "C:\\Users\\sunup\\PycharmProjects\\BinCENT\\lua\\src\\lgc.c",
    "pattern": "/^#define markobject(g,t) { if (iswhite(obj2gco(t))) \\\\$/",
    "language": "C",
    "line": 55,
    "kind": "macroparam",
    "scope": "markobject",
    "scopeKind": "macro",
    "roles": "def",
    "nth": 1
  },
  {
    "_type": "tag",
    "name": "t",
    "path": "C:\\Users\\sunup\\PycharmProjects\\BinCENT\\lua\\src\\lgc.c",
    "pattern": "/^void luaC_barrierback (lua_State *L, Table *t) {$/",
    "file": true,
    "language": "C",
    "line": 674,
    "typeref": "typename:Table *",
    "kind": "parameter",
    "scope": "luaC_barrierback",
    "scopeKind": "function",
    "roles": "def",
    "extras": "fileScope",
    "nth": 1
  },
  {
    "_type": "tag",
    "name": "th",
    "path": "C:\\Users\\sunup\\PycharmProjects\\BinCENT\\lua\\src\\lgc.c",
    "pattern": "/^      lua_State *th = gco2th(o);$/",
    "file": true,
    "language": "C",
    "line": 298,
    "typeref": "typename:lua_State *",
    "kind": "local",
    "scope": "propagatemark",
    "scopeKind": "function",
    "roles": "def",
    "extras": "fileScope",
    "end": 298
  },
  {
    "_type": "tag",
    "name": "tm",
    "path": "C:\\Users\\sunup\\PycharmProjects\\BinCENT\\lua\\src\\lgc.c",
    "pattern": "/^  const TValue *tm;$/",
    "file": true,
    "language": "C",
    "line": 449,
    "typeref": "typename:const TValue *",
    "kind": "local",
    "scope": "GCTM",
    "scopeKind": "function",
    "roles": "def",
    "extras": "fileScope",
    "end": 449
  },
  {
    "_type": "tag",
    "name": "traverseclosure",
    "path": "C:\\Users\\sunup\\PycharmProjects\\BinCENT\\lua\\src\\lgc.c",
    "pattern": "/^static void traverseclosure (global_State *g, Closure *cl) {$/",
    "file": true,
    "language": "C",
    "line": 224,
    "typeref": "typename:void",
    "kind": "function",
    "signature": "(global_State * g,Closure * cl)",
    "roles": "def",
    "extras": "fileScope",
    "end": 238
  },
  {
    "_type": "tag",
    "name": "traverseproto",
    "path": "C:\\Users\\sunup\\PycharmProjects\\BinCENT\\lua\\src\\lgc.c",
    "pattern": "/^static void traverseproto (global_State *g, Proto *f) {$/",
    "file": true,
    "language": "C",
    "line": 203,
    "typeref": "typename:void",
    "kind": "function",
    "signature": "(global_State * g,Proto * f)",
    "roles": "def",
    "extras": "fileScope",
    "end": 220
  },
  {
    "_type": "tag",
    "name": "traversestack",
    "path": "C:\\Users\\sunup\\PycharmProjects\\BinCENT\\lua\\src\\lgc.c",
    "pattern": "/^static void traversestack (global_State *g, lua_State *l) {$/",
    "file": true,
    "language": "C",
    "line": 256,
    "typeref": "typename:void",
    "kind": "function",
    "signature": "(global_State * g,lua_State * l)",
    "roles": "def",
    "extras": "fileScope",
    "end": 270
  },
  {
    "_type": "tag",
    "name": "traversetable",
    "path": "C:\\Users\\sunup\\PycharmProjects\\BinCENT\\lua\\src\\lgc.c",
    "pattern": "/^static int traversetable (global_State *g, Table *h) {$/",
    "file": true,
    "language": "C",
    "line": 158,
    "typeref": "typename:int",
    "kind": "function",
    "signature": "(global_State * g,Table * h)",
    "roles": "def",
    "extras": "fileScope",
    "end": 196
  },
  {
    "_type": "tag",
    "name": "tt",
    "path": "C:\\Users\\sunup\\PycharmProjects\\BinCENT\\lua\\src\\lgc.c",
    "pattern": "/^void luaC_link (lua_State *L, GCObject *o, lu_byte tt) {$/",
    "file": true,
    "language": "C",
    "line": 685,
    "typeref": "typename:lu_byte",
    "kind": "parameter",
    "scope": "luaC_link",
    "scopeKind": "function",
    "roles": "def",
    "extras": "fileScope",
    "nth": 2
  },
  {
    "_type": "tag",
    "name": "u",
    "path": "C:\\Users\\sunup\\PycharmProjects\\BinCENT\\lua\\src\\lgc.c",
    "pattern": "/^  GCObject *u = g->tmudata;$/",
    "file": true,
    "language": "C",
    "line": 116,
    "typeref": "typename:GCObject *",
    "kind": "local",
    "scope": "marktmu",
    "scopeKind": "function",
    "roles": "def",
    "extras": "fileScope",
    "end": 116
  },
  {
    "_type": "tag",
    "name": "u",
    "path": "C:\\Users\\sunup\\PycharmProjects\\BinCENT\\lua\\src\\lgc.c",
    "pattern": "/^#define isfinalized(u)\t\ttestbit((u)->marked, FINALIZEDBIT)$/",
    "language": "C",
    "line": 43,
    "kind": "macroparam",
    "scope": "isfinalized",
    "scopeKind": "macro",
    "roles": "def",
    "nth": 0
  },
  {
    "_type": "tag",
    "name": "u",
    "path": "C:\\Users\\sunup\\PycharmProjects\\BinCENT\\lua\\src\\lgc.c",
    "pattern": "/^#define markfinalized(u)\tl_setbit((u)->marked, FINALIZEDBIT)$/",
    "language": "C",
    "line": 44,
    "kind": "macroparam",
    "scope": "markfinalized",
    "scopeKind": "macro",
    "roles": "def",
    "nth": 0
  },
  {
    "_type": "tag",
    "name": "udata",
    "path": "C:\\Users\\sunup\\PycharmProjects\\BinCENT\\lua\\src\\lgc.c",
    "pattern": "/^  Udata *udata = rawgco2u(o);$/",
    "file": true,
    "language": "C",
    "line": 448,
    "typeref": "typename:Udata *",
    "kind": "local",
    "scope": "GCTM",
    "scopeKind": "function",
    "roles": "def",
    "extras": "fileScope",
    "end": 448
  },
  {
    "_type": "tag",
    "name": "udsize",
    "path": "C:\\Users\\sunup\\PycharmProjects\\BinCENT\\lua\\src\\lgc.c",
    "pattern": "/^  size_t udsize;  \\/* total size of userdata to be finalized *\\/$/",
    "file": true,
    "language": "C",
    "line": 527,
    "typeref": "typename:size_t",
    "kind": "local",
    "scope": "atomic",
    "scopeKind": "function",
    "roles": "def",
    "extras": "fileScope",
    "end": 527
  },
  {
    "_type": "tag",
    "name": "uv",
    "path": "C:\\Users\\sunup\\PycharmProjects\\BinCENT\\lua\\src\\lgc.c",
    "pattern": "/^      UpVal *uv = gco2uv(o);$/",
    "file": true,
    "language": "C",
    "line": 84,
    "typeref": "typename:UpVal *",
    "kind": "local",
    "scope": "reallymarkobject",
    "scopeKind": "function",
    "roles": "def",
    "extras": "fileScope",
    "end": 84
  },
  {
    "_type": "tag",
    "name": "uv",
    "path": "C:\\Users\\sunup\\PycharmProjects\\BinCENT\\lua\\src\\lgc.c",
    "pattern": "/^  UpVal *uv;$/",
    "file": true,
    "language": "C",
    "line": 516,
    "typeref": "typename:UpVal *",
    "kind": "local",
    "scope": "remarkupvals",
    "scopeKind": "function",
    "roles": "def",
    "extras": "fileScope",
    "end": 516
  },
  {
    "_type": "tag",
    "name": "uv",
    "path": "C:\\Users\\sunup\\PycharmProjects\\BinCENT\\lua\\src\\lgc.c",
    "pattern": "/^void luaC_linkupval (lua_State *L, UpVal *uv) {$/",
    "file": true,
    "language": "C",
    "line": 694,
    "typeref": "typename:UpVal *",
    "kind": "parameter",
    "scope": "luaC_linkupval",
    "scopeKind": "function",
    "roles": "def",
    "extras": "fileScope",
    "nth": 1
  },
  {
    "_type": "tag",
    "name": "v",
    "path": "C:\\Users\\sunup\\PycharmProjects\\BinCENT\\lua\\src\\lgc.c",
    "pattern": "/^void luaC_barrierf (lua_State *L, GCObject *o, GCObject *v) {$/",
    "file": true,
    "language": "C",
    "line": 661,
    "typeref": "typename:GCObject *",
    "kind": "parameter",
    "scope": "luaC_barrierf",
    "scopeKind": "function",
    "roles": "def",
    "extras": "fileScope",
    "nth": 2
  },
  {
    "_type": "tag",
    "name": "weakkey",
    "path": "C:\\Users\\sunup\\PycharmProjects\\BinCENT\\lua\\src\\lgc.c",
    "pattern": "/^  int weakkey = 0;$/",
    "file": true,
    "language": "C",
    "line": 160,
    "typeref": "typename:int",
    "kind": "local",
    "scope": "traversetable",
    "scopeKind": "function",
    "roles": "def",
    "extras": "fileScope",
    "end": 160
  },
  {
    "_type": "tag",
    "name": "weakvalue",
    "path": "C:\\Users\\sunup\\PycharmProjects\\BinCENT\\lua\\src\\lgc.c",
    "pattern": "/^  int weakvalue = 0;$/",
    "file": true,
    "language": "C",
    "line": 161,
    "typeref": "typename:int",
    "kind": "local",
    "scope": "traversetable",
    "scopeKind": "function",
    "roles": "def",
    "extras": "fileScope",
    "end": 161
  },
  {
    "_type": "tag",
    "name": "white2gray",
    "path": "C:\\Users\\sunup\\PycharmProjects\\BinCENT\\lua\\src\\lgc.c",
    "pattern": "/^#define white2gray(/",
    "file": true,
    "language": "C",
    "line": 37,
    "kind": "macro",
    "signature": "(x)",
    "roles": "def",
    "extras": "fileScope",
    "end": 37
  },
  {
    "_type": "tag",
    "name": "x",
    "path": "C:\\Users\\sunup\\PycharmProjects\\BinCENT\\lua\\src\\lgc.c",
    "pattern": "/^#define black2gray(x)\tresetbit((x)->gch.marked, BLACKBIT)$/",
    "language": "C",
    "line": 38,
    "kind": "macroparam",
    "scope": "black2gray",
    "scopeKind": "macro",
    "roles": "def",
    "nth": 0
  },
  {
    "_type": "tag",
    "name": "x",
    "path": "C:\\Users\\sunup\\PycharmProjects\\BinCENT\\lua\\src\\lgc.c",
    "pattern": "/^#define makewhite(g,x)\t\\\\$/",
    "language": "C",
    "line": 34,
    "kind": "macroparam",
    "scope": "makewhite",
    "scopeKind": "macro",
    "roles": "def",
    "nth": 1
  },
  {
    "_type": "tag",
    "name": "x",
    "path": "C:\\Users\\sunup\\PycharmProjects\\BinCENT\\lua\\src\\lgc.c",
    "pattern": "/^#define white2gray(x)\treset2bits((x)->gch.marked, WHITE0BIT, WHITE1BIT)$/",
    "language": "C",
    "line": 37,
    "kind": "macroparam",
    "scope": "white2gray",
    "scopeKind": "macro",
    "roles": "def",
    "nth": 0
  }
]